CHANGES.rst
MANIFEST.in
README.rst
buildout.cfg
requirements-coverage.txt
requirements-tests.txt
setup.py
docs/LICENSE.GPL
docs/LICENSE.txt
src/EXTERNALS.txt
src/Products/__init__.py
src/Products.MeetingCharleroi.egg-info/PKG-INFO
src/Products.MeetingCharleroi.egg-info/SOURCES.txt
src/Products.MeetingCharleroi.egg-info/dependency_links.txt
src/Products.MeetingCharleroi.egg-info/namespace_packages.txt
src/Products.MeetingCharleroi.egg-info/not-zip-safe
src/Products.MeetingCharleroi.egg-info/requires.txt
src/Products.MeetingCharleroi.egg-info/top_level.txt
src/Products/MeetingCharleroi/README.txt
src/Products/MeetingCharleroi/__init__.py
src/Products/MeetingCharleroi/adapters.py
src/Products/MeetingCharleroi/config.py
src/Products/MeetingCharleroi/configure.zcml
src/Products/MeetingCharleroi/events.py
src/Products/MeetingCharleroi/events.zcml
src/Products/MeetingCharleroi/indexes.py
src/Products/MeetingCharleroi/interfaces.py
src/Products/MeetingCharleroi/meeting.py
src/Products/MeetingCharleroi/overrides.zcml
src/Products/MeetingCharleroi/profiles.zcml
src/Products/MeetingCharleroi/refresh.txt
src/Products/MeetingCharleroi/setuphandlers.py
src/Products/MeetingCharleroi/testing.py
src/Products/MeetingCharleroi/testing.zcml
src/Products/MeetingCharleroi/utils.py
src/Products/MeetingCharleroi/version.txt
src/Products/MeetingCharleroi/vocabularies.py
src/Products/MeetingCharleroi/Extensions/__init__.py
src/Products/MeetingCharleroi/Extensions/importGroupsUserAndRoles.ods
src/Products/MeetingCharleroi/Extensions/utils.py
src/Products/MeetingCharleroi/browser/__init__.py
src/Products/MeetingCharleroi/browser/configure.zcml
src/Products/MeetingCharleroi/browser/overrides.py
src/Products/MeetingCharleroi/faceted_conf/meetingcharleroi_dashboard_items_widgets.xml
src/Products/MeetingCharleroi/locales/PloneMeeting.pot
src/Products/MeetingCharleroi/locales/imio.actionspanel.pot
src/Products/MeetingCharleroi/locales/imio.history.pot
src/Products/MeetingCharleroi/locales/plone.pot
src/Products/MeetingCharleroi/locales/sync_pos.sh
src/Products/MeetingCharleroi/locales/de/LC_MESSAGES/PloneMeeting.po
src/Products/MeetingCharleroi/locales/de/LC_MESSAGES/imio.actionspanel.po
src/Products/MeetingCharleroi/locales/de/LC_MESSAGES/imio.history.po
src/Products/MeetingCharleroi/locales/de/LC_MESSAGES/plone.po
